CHANGELOG.md
LICENSE
README.md
as7343/__init__.py
as7343/__main__.py
pimoroni_as7343-0.0.2.dist-info/METADATA
pimoroni_as7343-0.0.2.dist-info/WHEEL
pimoroni_as7343-0.0.2.dist-info/licenses/LICENSE
pimoroni_as7343-0.0.2.dist-info/RECORD
